[
  {
    "index": 0,
    "emotion": "joy",
    "objects": [],
    "spatial": "neutral",
    "color": "#FFEB3B",
    "accent": "#FF9800",
    "geometry": "box",
    "scale": 1.0,
    "height": 2.5,
    "position": {
      "x": 3.2,
      "y": 1.25,
      "z": 0.0
    },
    "snippet": "I remember my first day of school. I was nervous but excited.",
    "date": "2026-07-06 19:02"
  },
  {
    "index": 1,
    "emotion": "nostalgia",
    "objects": [
      "school",
      "classroom",
      "hallway",
      "backpack"
    ],
    "spatial": "open",
    "color": "#AB47BC",
    "accent": "#7B1FA2",
    "geometry": "cylinder",
    "scale": 1.4,
    "height": 3.1,
    "position": {
      "x": -3.34,
      "y": 1.55,
      "z": 3.06
    },
    "snippet": "last day of school",
    "date": "2026-07-06 19:11"
  },
  {
    "index": 2,
    "emotion": "nostalgia",
    "objects": [
      "school",
      "classroom",
      "desk",
      "lockers"
    ],
    "spatial": "crowded",
    "color": "#AB47BC",
    "accent": "#7B1FA2",
    "geometry": "cylinder",
    "scale": 0.7,
    "height": 2.05,
    "position": {
      "x": 0.48,
      "y": 1.02,
      "z": -5.52
    },
    "snippet": "my last day of school",
    "date": "2026-07-06 19:44"
  },
  {
    "index": 3,
    "emotion": "nostalgia",
    "objects": [
      "school",
      "classroom",
      "lockers",
      "desk"
    ],
    "spatial": "crowded",
    "color": "#AB47BC",
    "accent": "#7B1FA2",
    "geometry": "cylinder",
    "scale": 0.7,
    "height": 2.69,
    "position": {
      "x": 3.89,
      "y": 1.35,
      "z": 5.08
    },
    "snippet": "last day of school",
    "date": "2026-07-06 19:55"
  },
  {
    "index": 4,
    "emotion": "nostalgia",
    "objects": [
      "college",
      "dorm",
      "lecture hall"
    ],
    "spatial": "crowded",
    "color": "#AB47BC",
    "accent": "#7B1FA2",
    "geometry": "box",
    "scale": 0.7,
    "height": 7.23,
    "position": {
      "x": -7.05,
      "y": 3.61,
      "z": -1.25
    },
    "snippet": "last day of college",
    "date": "2026-07-06 20:08"
  },
  {
    "index": 5,
    "emotion": "nostalgia",
    "objects": [
      "school",
      "classroom",
      "hallway"
    ],
    "spatial": "crowded",
    "color": "#AB47BC",
    "accent": "#7B1FA2",
    "geometry": "cylinder",
    "scale": 0.7,
    "height": 8.99,
    "position": {
      "x": 6.61,
      "y": 4.49,
      "z": -4.21
    },
    "snippet": "last day of school",
    "date": "2026-07-06 20:17"
  },
  {
    "index": 6,
    "emotion": "nostalgia",
    "objects": [
      "calendar",
      "clock"
    ],
    "spatial": "neutral",
    "color": "#AB47BC",
    "accent": "#F06292",
    "geometry": "box",
    "scale": 1.0,
    "height": 10.18,
    "position": {
      "x": -2.2,
      "y": 5.09,
      "z": 8.18
    },
    "snippet": "last day of year",
    "date": "2026-07-06 20:30"
  },
  {
    "index": 7,
    "emotion": "neutral",
    "objects": [
      "calendar",
      "date",
      "month"
    ],
    "spatial": "neutral",
    "color": "#B0BEC5",
    "accent": "#4DD0E1",
    "geometry": "box",
    "scale": 1.0,
    "height": 10.27,
    "position": {
      "x": -4.17,
      "y": 5.13,
      "z": -8.03
    },
    "snippet": "last day of month",
    "date": "2026-07-06 20:40"
  },
  {
    "index": 8,
    "emotion": "fear",
    "objects": [
      "college",
      "campus",
      "classroom"
    ],
    "spatial": "crowded",
    "color": "#37474F",
    "accent": "#00E676",
    "geometry": "box",
    "scale": 0.7,
    "height": 42.42,
    "position": {
      "x": 9.02,
      "y": 21.21,
      "z": 3.29
    },
    "snippet": "my 1st day in college and I am so nervous",
    "date": "2026-07-06 20:54"
  },
  {
    "index": 9,
    "emotion": "joy",
    "objects": [
      "clock",
      "fireworks",
      "people"
    ],
    "spatial": "crowded",
    "color": "#FFEB3B",
    "accent": "#FF6D00",
    "geometry": "box",
    "scale": 0.7,
    "height": 36.4,
    "position": {
      "x": -9.35,
      "y": 18.2,
      "z": 3.86
    },
    "snippet": "the new year",
    "date": "2026-07-06 21:10"
  }
]